[{"i":1,"n":true,"q":"obsess","to":"迷恋","am":"əbˈses","en":"əbˈses","dt":1645547409926},{"i":1,"n":true,"q":"techceleration","to":"技术加速","am":"","en":"","dt":1645547349240},{"i":1,"n":true,"q":"cardiology","to":"心脏病学","am":"ˌkɑːdiˈɒlədʒi","en":"ˌkɑːrdiˈɑːlədʒi","dt":1645547334833},{"i":1,"n":true,"q":"waterproof","to":"不透水的","am":"ˈwɔːtəpruːf","en":"ˈwɔːtərpruːf","dt":1645547263614},{"i":1,"n":true,"q":"laymen","to":"外行","am":"ˈleɪmən","en":"ˈleɪmən","dt":1645547155794},{"i":1,"n":true,"q":"mammography","to":"乳房X光检查","am":"mæˈmɒɡrəfi","en":"mæˈmɑːɡrəfi","dt":1645547124758},{"i":1,"n":true,"q":"ardent","to":"adj.热烈的,激情的","am":"ˈɑːd(ə)nt","en":"ˈɑːrd(ə)nt","dt":1645546879180},{"i":1,"n":true,"q":"inadmissibility","to":"n.不许可的事，难承认的事,不允许","am":"ˈɪnədˌmɪsəˈbɪlɪti","en":"ˈɪnədˌmɪsəˈbɪləti","dt":1645546674992},{"i":1,"n":true,"q":"paycheck","to":"n.付薪水的支票，薪水","am":"'peɪtʃek","en":"ˈpeɪtʃek","dt":1645546404853},{"i":1,"n":true,"q":"innervating","to":"支配","am":"ˈɪnɜːˌveɪt","en":"ɪˈnɜːrvet","dt":1645546354155},{"i":1,"n":true,"q":"spectating","to":"观看","en":"spekˈteɪtɪŋ","dt":1645546293742},{"i":1,"n":true,"q":"bespoke","to":"定制","am":"bɪˈspəʊk","en":"bɪˈspoʊk","dt":1645546158601},{"i":1,"n":true,"q":"astounds","to":"震惊","am":"əˈstaʊnd","en":"əˈstaʊnd","dt":1645546076936},{"i":1,"n":true,"q":"trickster","to":"n.骗子，无赖","am":"ˈtrɪkstə(r)","en":"ˈtrɪkstər","dt":1645546064763},{"i":1,"n":true,"q":"disadvantaged","to":"弱势群体","am":"ˌdɪsədˈvɑːntɪdʒd","en":"ˌdɪsədˈvæntɪdʒd","dt":1645545751137},{"i":1,"n":true,"q":"outcasts","to":"抛弃","en":"ˈaʊtkæsts","dt":1645545417218},{"i":1,"n":true,"q":"motocross","to":"摩托车越野赛","am":"ˈməʊtəʊkrɒs","en":"ˈmoʊtoʊkrɔːs","dt":1645545216727},{"i":1,"n":true,"q":"myth","to":"神话","am":"mɪθ","en":"mɪθ","dt":1645544939691},{"i":1,"n":true,"q":"howling","to":"咆哮","am":"ˈhaʊlɪŋ","en":"ˈhaʊlɪŋ","dt":1645544912912},{"i":1,"n":true,"q":"delight","to":"v.使高兴;n.高兴,乐事","am":"dɪˈlaɪt","en":"dɪˈlaɪt","dt":1645544895443},{"i":1,"n":true,"q":"stranglehold","to":"n.勒颈,压制,束缚","am":"ˈstræŋɡlhəʊld","en":"ˈstræŋɡlhoʊld","dt":1645544783646},{"i":1,"n":true,"q":"hunkering","to":"躲藏在","am":"ˈhʌŋkə(r)","en":"ˈhʌŋkər","dt":1645544740699},{"i":1,"n":true,"q":"tumbling","to":"暴跌","am":"ˈtʌmblɪŋ","en":"ˈtʌmblɪŋ","dt":1645544200095},{"i":1,"n":true,"q":"stiffen","to":"变硬","am":"ˈstɪf(ə)n","en":"ˈstɪfn","dt":1645543881144},{"i":1,"n":true,"q":"prostate","to":"前列腺","am":"ˈprɒsteɪt","en":"ˈprɑːsteɪt","dt":1645543442086},{"i":1,"n":true,"q":"pancreatic","to":"adj.胰腺的","am":"ˌpæŋkriˈætɪk","en":"ˌpæŋkriˈætɪk","dt":1645543436090},{"i":1,"n":true,"q":"aviator","to":"飞行员","am":"ˈeɪvieɪtə(r)","en":"ˈeɪvieɪtər","dt":1645543426913},{"i":1,"n":true,"q":"fed up","to":"adj. 对…感到厌烦[不满] 的,烦透了，受够了","am":"ˌfed ˈʌp","en":"fed ʌp","dt":1645543365765},{"i":1,"n":true,"q":"practitioner","to":"n.从业者,执业医生,习艺者,专门人才","am":"prækˈtɪʃənə(r)","en":"prækˈtɪʃənər","dt":1645543304268},{"i":1,"n":true,"q":"stumbling","to":"绊倒","am":"'stʌmbliŋ","en":"ˈstʌmblɪŋ","dt":1645543283271},{"i":1,"n":true,"q":"decree","to":"法令","am":"dɪˈkriː","en":"dɪˈkriː","dt":1645540339901},{"i":1,"n":true,"q":"proportionate","to":"成比例的","am":"prəˈpɔːʃənət","en":"prəˈpɔːrʃənət","dt":1645540041047},{"i":1,"n":true,"q":"rodent","to":"啮齿动物","am":"ˈrəʊdnt","en":"ˈroʊdnt","dt":1645539924180},{"i":1,"n":true,"q":"catastrophe","to":"灾难","am":"kəˈtæstrəfi","en":"kəˈtæstrəfi","dt":1645539829741},{"i":1,"n":true,"q":"hip","to":"臀部","am":"hɪp","en":"hɪp","dt":1645539750765},{"i":1,"n":true,"q":"echelon","to":"梯队","am":"ˈeʃəlɒn","en":"ˈeʃəlɑːn","dt":1645539663347},{"i":1,"n":true,"q":"blackmail","to":"勒索","am":"ˈblækmeɪl","en":"ˈblækmeɪl","dt":1645539517581}]